sdcf/__init__.py
sdcf/cli.py
sdcf/main.py
sdcf-0.2.0.dist-info/METADATA
sdcf-0.2.0.dist-info/WHEEL
sdcf-0.2.0.dist-info/entry_points.txt
sdcf-0.2.0.dist-info/top_level.txt
sdcf-0.2.0.dist-info/RECORD
